pass_secret_service/__init__.py
pass_secret_service/pass_secret_service.py
pass_secret_service/common/__init__.py
pass_secret_service/common/consts.py
pass_secret_service/common/debug.py
pass_secret_service/common/exceptions.py
pass_secret_service/common/names.py
pass_secret_service/common/pass_store.py
pass_secret_service/common/tools.py
pass_secret_service/interfaces/__init__.py
pass_secret_service/interfaces/collection.py
pass_secret_service/interfaces/item.py
pass_secret_service/interfaces/service.py
pass_secret_service/interfaces/session.py
pass_secret_service-0.1a0.dist-info/DESCRIPTION.rst
pass_secret_service-0.1a0.dist-info/METADATA
pass_secret_service-0.1a0.dist-info/RECORD
pass_secret_service-0.1a0.dist-info/WHEEL
pass_secret_service-0.1a0.dist-info/entry_points.txt
pass_secret_service-0.1a0.dist-info/metadata.json
pass_secret_service-0.1a0.dist-info/top_level.txt
