Metadata-Version: 2.0
Name: pass-secret-service
Version: 0.1a0
Summary: [![Build Status](https://travis-ci.org/mdellweg/pass_secret_service.svg?branch=master)](https://travis-ci.org/mdellweg/pass_secret_service)
Requires-Dist: click
Requires-Dist: decorator
Requires-Dist: pydbus
Requires-Dist: pygobject
Requires-Dist: pypass
Requires-Dist: simplejson
